aiverify_fairness_metrics_toolbox_for_regression/__init__.py
aiverify_fairness_metrics_toolbox_for_regression/__main__.py
aiverify_fairness_metrics_toolbox_for_regression/algo.meta.json
aiverify_fairness_metrics_toolbox_for_regression/algo.py
aiverify_fairness_metrics_toolbox_for_regression/algo_init.py
aiverify_fairness_metrics_toolbox_for_regression/input.schema.json
aiverify_fairness_metrics_toolbox_for_regression/output.schema.json
aiverify_fairness_metrics_toolbox_for_regression/plugin_init.py
aiverify_fairness_metrics_toolbox_for_regression-2.1.0.dist-info/METADATA
aiverify_fairness_metrics_toolbox_for_regression-2.1.0.dist-info/WHEEL
aiverify_fairness_metrics_toolbox_for_regression-2.1.0.dist-info/entry_points.txt
aiverify_fairness_metrics_toolbox_for_regression-2.1.0.dist-info/licenses/AUTHORS.rst
aiverify_fairness_metrics_toolbox_for_regression-2.1.0.dist-info/licenses/LICENSE
aiverify_fairness_metrics_toolbox_for_regression-2.1.0.dist-info/licenses/NOTICE.md
aiverify_fairness_metrics_toolbox_for_regression-2.1.0.dist-info/RECORD
