Metadata-Version: 2.4
Name: aiverify-fairness-metrics-toolbox-for-regression
Version: 2.1.0
Summary: AI Verify Fairness Metrics Toolbox (FMT) for Regression contains a list of fairness metrics used to measure how resources (e.g. opportunities, food, loan, medical help) are allocated among the demographic groups (e.g. married male, married female) given a set of sensitive feature(s) (e.g. gender, marital status). This plugin is developed for regression models.
Author: AI Verify
License-File: AUTHORS.rst
License-File: LICENSE
License-File: NOTICE.md
Requires-Python: <3.13,>=3.10
Requires-Dist: aiverify-test-engine>=2.1.0
Requires-Dist: joblib==1.4.2
Requires-Dist: numpy==1.26.4
Requires-Dist: pandas==2.2.2
Requires-Dist: scikit-learn==1.5.2
